basiq/API.py
basiq/HTTPError.py
basiq/Session.py
basiq/__init__.py
basiq/services/ConnectionService.py
basiq/services/UserService.py
basiq/services/__init__.py
basiq/utils/FilterBuilder.py
basiq/utils/__init__.py
basiq-1.0.0.dist-info/METADATA
basiq-1.0.0.dist-info/RECORD
basiq-1.0.0.dist-info/WHEEL
basiq-1.0.0.dist-info/top_level.txt
