Metadata-Version: 2.1
Name: basiq
Version: 1.0.0
Summary: SDK Package for Basiq's HTTP API
Home-page: https://github.com/basiqio/basiq-sdk-python
Author: Nenad Lukic
Author-email: nenad@basiq.io
License: UNKNOWN
Download-URL: https://github.com/basiqio/basiq-sdk-python/archive/1.0.0.tar.gz
Keywords: basiq,finance,sdk,api
Platform: UNKNOWN
Requires-Python: >=3
Requires-Dist: requests
